callsignlookuptools/__info__.py
callsignlookuptools/__init__.py
callsignlookuptools/__main__.py
callsignlookuptools/cli.py
callsignlookuptools/py.typed
callsignlookuptools/callook/__init__.py
callsignlookuptools/callook/callook.py
callsignlookuptools/callook/callookasync.py
callsignlookuptools/callook/callooksync.py
callsignlookuptools/common/__init__.py
callsignlookuptools/common/abcs.py
callsignlookuptools/common/constants.py
callsignlookuptools/common/dataclasses.py
callsignlookuptools/common/enums.py
callsignlookuptools/common/exceptions.py
callsignlookuptools/common/functions.py
callsignlookuptools/common/mixins.py
callsignlookuptools/hamqth/__init__.py
callsignlookuptools/hamqth/hamqth.py
callsignlookuptools/hamqth/hamqthasync.py
callsignlookuptools/hamqth/hamqthsync.py
callsignlookuptools/qrz/__init__.py
callsignlookuptools/qrz/qrz.py
callsignlookuptools/qrz/qrzasync.py
callsignlookuptools/qrz/qrzsync.py
callsignlookuptools/qrzcq/__init__.py
callsignlookuptools/qrzcq/qrzcq.py
callsignlookuptools/qrzcq/qrzcqasync.py
callsignlookuptools/qrzcq/qrzcqsync.py
callsignlookuptools-1.1.2.dist-info/licenses/LICENSE
tests/common/__init__.py
tests/common/test_dataclasses.py
tests/common/test_functions.py
callsignlookuptools-1.1.2.dist-info/METADATA
callsignlookuptools-1.1.2.dist-info/WHEEL
callsignlookuptools-1.1.2.dist-info/top_level.txt
callsignlookuptools-1.1.2.dist-info/RECORD
