Metadata-Version: 2.4
Name: callsignlookuptools
Version: 1.1.2
Summary: QRZ, Callook, HamQTH, and QRZCQ API interface with sync and async support
Home-page: https://callsignlookuptools.miaow.io
Author: classabbyamp, 0x5c
Author-email: dev@placeviolette.net, dev@0x5c.io
License: BSD 3-Clause
Classifier: License :: OSI Approved :: BSD License
Classifier: Programming Language :: Python :: 3
Classifier: Programming Language :: Python :: 3.9
Classifier: Programming Language :: Python :: 3.10
Classifier: Programming Language :: Python :: 3.11
Classifier: Development Status :: 5 - Production/Stable
Classifier: Environment :: Console
Classifier: Intended Audience :: Developers
Classifier: Operating System :: OS Independent
Classifier: Topic :: Communications :: Ham Radio
Classifier: Framework :: AsyncIO
Requires-Python: >=3.9
License-File: LICENSE
Requires-Dist: lxml
Requires-Dist: gridtools
Requires-Dist: pydantic>=2.0
Requires-Dist: requests; extra != "async"
Provides-Extra: cli
Requires-Dist: typer[all]; extra == "cli"
Provides-Extra: async
Requires-Dist: aiohttp; extra == "async"
Provides-Extra: all
Requires-Dist: aiohttp; extra == "all"
Dynamic: author
Dynamic: author-email
Dynamic: classifier
Dynamic: description
Dynamic: description-content-type
Dynamic: home-page
Dynamic: license
Dynamic: license-file
Dynamic: provides-extra
Dynamic: requires-dist
Dynamic: requires-python
Dynamic: summary
